suite_py/__init__.py
suite_py/__version__.py
suite_py/cli.py
suite_py/commands/__init__.py
suite_py/commands/ask_review.py
suite_py/commands/bump.py
suite_py/commands/check.py
suite_py/commands/common.py
suite_py/commands/context.py
suite_py/commands/create_branch.py
suite_py/commands/estimate_cone.py
suite_py/commands/login.py
suite_py/commands/merge_pr.py
suite_py/commands/open_pr.py
suite_py/commands/project_lock.py
suite_py/commands/release.py
suite_py/commands/set_token.py
suite_py/commands/status.py
suite_py/lib/__init__.py
suite_py/lib/config.py
suite_py/lib/handler/__init__.py
suite_py/lib/handler/aws_handler.py
suite_py/lib/handler/captainhook_handler.py
suite_py/lib/handler/changelog_handler.py
suite_py/lib/handler/frequent_reviewers_handler.py
suite_py/lib/handler/git_handler.py
suite_py/lib/handler/github_handler.py
suite_py/lib/handler/metrics_handler.py
suite_py/lib/handler/okta_handler.py
suite_py/lib/handler/pre_commit_handler.py
suite_py/lib/handler/prompt_utils.py
suite_py/lib/handler/version_handler.py
suite_py/lib/handler/youtrack_handler.py
suite_py/lib/logger.py
suite_py/lib/metrics.py
suite_py/lib/oauth.py
suite_py/lib/requests/__init__.py
suite_py/lib/requests/auth.py
suite_py/lib/requests/session.py
suite_py/lib/symbol.py
suite_py/lib/tokens.py
suite_py/templates/login.html
suite_py-1.50.0.dist-info/METADATA
suite_py-1.50.0.dist-info/WHEEL
suite_py-1.50.0.dist-info/entry_points.txt
suite_py-1.50.0.dist-info/RECORD
