Metadata-Version: 2.1
Name: suite-py
Version: 1.50.0
Summary: 
Author: larrywax, EugenioLaghi, michelangelomo
Author-email: devops@prima.it
Requires-Python: >=3.8,<4.0
Classifier: Programming Language :: Python :: 3
Classifier: Programming Language :: Python :: 3.8
Classifier: Programming Language :: Python :: 3.9
Classifier: Programming Language :: Python :: 3.10
Classifier: Programming Language :: Python :: 3.11
Classifier: Programming Language :: Python :: 3.12
Requires-Dist: Click (>=7.0)
Requires-Dist: InquirerPy (>=0.2.0)
Requires-Dist: PyGithub (>=1.57)
Requires-Dist: PyYaml (>=5.4)
Requires-Dist: autoupgrade-prima (>=0.6)
Requires-Dist: boto3 (>=1.17.84)
Requires-Dist: cement (>=3.0)
Requires-Dist: colorama (>=0.4.3)
Requires-Dist: halo (>=0.0.28)
Requires-Dist: inquirer (>=3.1.4,<4.0.0)
Requires-Dist: itsdangerous (==2.2.0)
Requires-Dist: keyring (>=23.9.1,<26.0.0)
Requires-Dist: pylint (>=2.14.5,<4.0.0)
Requires-Dist: pytest (>=7.0.0)
Requires-Dist: python-dateutil (>=2.8.2)
Requires-Dist: requests (>=2.26.0)
Requires-Dist: requests-toolbelt (>=0.9.1)
Requires-Dist: rich (==14.2.0)
Requires-Dist: semver (>=3.0.4,<4.0.0)
Requires-Dist: termcolor (>=1.1.0)
Requires-Dist: truststore (>=0.7,<0.11) ; python_version >= "3.10"
